chrome_bookmarks/__init__.py
chrome_bookmarks-2019.3.31.dist-info/METADATA
chrome_bookmarks-2019.3.31.dist-info/WHEEL
chrome_bookmarks-2019.3.31.dist-info/top_level.txt
chrome_bookmarks-2019.3.31.dist-info/RECORD
