Metadata-Version: 2.1
Name: chrome-bookmarks
Version: 2019.3.31
Summary: Google Chrome bookmarks helper
Home-page: https://github.com/looking-for-a-job/chrome-bookmarks.py
License: UNKNOWN
Keywords: Google Chrome bookmarks
Platform: UNKNOWN
Classifier: License :: Public Domain
Classifier: Operating System :: OS Independent
Classifier: Programming Language :: Python
Classifier: Programming Language :: Python :: 2
Classifier: Programming Language :: Python :: 2.7
Classifier: Programming Language :: Python :: 3
Classifier: Programming Language :: Python :: 3.4
Classifier: Programming Language :: Python :: 3.5
Classifier: Programming Language :: Python :: 3.6
Classifier: Programming Language :: Python :: 3.7
Classifier: Topic :: Software Development
Requires-Dist: public
Requires-Dist: setuptools
